<?xml version="1.0" encoding="UTF-8"?>
<objects serializationModel="Studio.02.00.00">
	<object class="AudioFile" id="{ab0bf857-094a-4132-a4cc-11c4df846a19}">
		<property name="assetPath">
			<value>characters/player/sfx_uni_player_movement_glide_01.wav</value>
		</property>
		<property name="isStreaming">
			<value>true</value>
		</property>
		<property name="frequencyInKHz">
			<value>48</value>
		</property>
		<property name="channelCount">
			<value>1</value>
		</property>
		<property name="length">
			<value>11.269104166666667</value>
		</property>
		<relationship name="masterAssetFolder">
			<destination>{bc839046-d7c7-4a97-96b4-932bd50751bc}</destination>
		</relationship>
	</object>
</objects>
